PyPadding-1.0.3.dist-info/METADATA
PyPadding-1.0.3.dist-info/RECORD
PyPadding-1.0.3.dist-info/WHEEL
PyPadding-1.0.3.dist-info/top_level.txt
pypadding/__init__.py
pypadding/base.py
pypadding/iso10126.py
pypadding/iso7816_4.py
pypadding/pkcs.py
pypadding/x923.py
