Metadata-Version: 2.1
Name: PyPadding
Version: 1.0.3
Summary: Padding package when using block cryptography
Home-page: https://github.com/blinglnav/pypadding
Author: Min Choro
Author-email: blinglnav@gmail.com
License: UNKNOWN
Keywords: Padding,Cryptography,Encrypt,Decrypt,PKCS,PKCS#5,PKCS#7,ANSI x923,ISO 10126,ISO/IEC 7816-4
Platform: UNKNOWN
Classifier: Programming Language :: Python :: 3
Classifier: Programming Language :: Python :: 3.2
Classifier: Programming Language :: Python :: 3.3
Classifier: Programming Language :: Python :: 3.4
Classifier: Programming Language :: Python :: 3.5
Classifier: Programming Language :: Python :: 3.6
Requires-Python: >=3
